rainbowlist/__init__.py
rainbowlist/main.py
rainbowlist/weak.py
rainbowlist-0.1.0.dist-info/WHEEL
rainbowlist-0.1.0.dist-info/METADATA
rainbowlist-0.1.0.dist-info/RECORD
