Metadata-Version: 2.1
Name: rainbowlist
Version: 0.1.0
Summary: Rainbow Lists
Keywords: simulation
Requires-Python: >=3.7
Classifier: Topic :: Software Development
Classifier: Programming Language :: Python :: 3
Project-URL: Homepage, https://github.com/asvarga/RainbowList
